magnus_extensions/.DS_Store
magnus_extensions/aws.py
magnus_extensions/catalog/k8s_pvc/implementation.py
magnus_extensions/catalog/k8s_pvc/integration.py
magnus_extensions/catalog/s3/implementation.py
magnus_extensions/catalog/s3/integration.py
magnus_extensions/datastore/chunked_k8s_pvc/implementation.py
magnus_extensions/datastore/chunked_k8s_pvc/integration.py
magnus_extensions/datastore/chunked_s3/implementation.py
magnus_extensions/datastore/chunked_s3/integration.py
magnus_extensions/datastore/db/implementation.py
magnus_extensions/datastore/db/integration.py
magnus_extensions/datastore/k8s_pvc/implementation.py
magnus_extensions/datastore/k8s_pvc/integration.py
magnus_extensions/datastore/s3/implementation.py
magnus_extensions/datastore/s3/integration.py
magnus_extensions/executor/argo/implementation.py
magnus_extensions/executor/argo/integration.py
magnus_extensions/executor/k8s_job/implementation.py
magnus_extensions/executor/k8s_job/integration.py
magnus_extensions/executor/kubeflow/implementation.py
magnus_extensions/executor/kubeflow/integration.py
magnus_extensions/executor/slurm/implementation.py
magnus_extensions/executor/slurm/integration.py
magnus_extensions/executor/slurm_job/implementation.py
magnus_extensions/executor/slurm_job/integration.py
magnus_extensions/experiment_tracker/mlflow/implementation.py
magnus_extensions/magnus_extension_template/implementation.py
magnus_extensions/magnus_extension_template/integration.py
magnus_extensions/secrets/aws/implementation.py
magnus_extensions/secrets/aws/integration.py
magnus_extensions-0.2.13.dist-info/LICENSE
magnus_extensions-0.2.13.dist-info/METADATA
magnus_extensions-0.2.13.dist-info/WHEEL
magnus_extensions-0.2.13.dist-info/entry_points.txt
magnus_extensions-0.2.13.dist-info/RECORD
