Metadata-Version: 2.1
Name: magnus_extensions
Version: 0.2.13
Summary: Extensions to Magnus core
License: Apache-2.0
Author: Vijay Vammi
Author-email: mesanthu@gmail.com
Requires-Python: >=3.7,<4.0
Classifier: License :: OSI Approved :: Apache Software License
Classifier: Programming Language :: Python :: 3
Classifier: Programming Language :: Python :: 3.7
Classifier: Programming Language :: Python :: 3.8
Classifier: Programming Language :: Python :: 3.9
Classifier: Programming Language :: Python :: 3.10
Classifier: Programming Language :: Python :: 3.11
Provides-Extra: aws
Provides-Extra: database
Provides-Extra: k8s
Provides-Extra: kubeflow
Provides-Extra: mlflow
Requires-Dist: boto3 ; extra == "aws"
Requires-Dist: kfp (>=1.8.18,<2.0.0) ; extra == "kubeflow"
Requires-Dist: kubernetes ; extra == "k8s"
Requires-Dist: magnus (>=0.4.12,<0.5.0)
Requires-Dist: mlflow-skinny ; extra == "mlflow"
Requires-Dist: sqlalchemy ; extra == "database"
